ncRNABert/__init__.py
ncRNABert/model.py
ncRNABert/modules.py
ncRNABert/pretrain.py
ncRNABert/utils.py
ncrnabert-0.1.4.dist-info/licenses/LICENSE
ncrnabert-0.1.4.dist-info/METADATA
ncrnabert-0.1.4.dist-info/WHEEL
ncrnabert-0.1.4.dist-info/top_level.txt
ncrnabert-0.1.4.dist-info/RECORD
