Metadata-Version: 2.4
Name: ncRNABert
Version: 0.1.4
Summary: ncRNA language model
Home-page: https://github.com/wangleiofficial/ncRNABert
Author: Lei Wang
Author-email: wanglei@isyslab.org
License: MIT
Keywords: ncRNA language model
Classifier: Development Status :: 3 - Alpha
Classifier: Intended Audience :: Developers
Classifier: License :: OSI Approved :: MIT License
Classifier: Programming Language :: Python :: 3
License-File: LICENSE
Requires-Dist: einops
Requires-Dist: torch
Requires-Dist: numpy
Requires-Dist: rotary_embedding_torch
Dynamic: author
Dynamic: author-email
Dynamic: classifier
Dynamic: description
Dynamic: description-content-type
Dynamic: home-page
Dynamic: keywords
Dynamic: license
Dynamic: license-file
Dynamic: requires-dist
Dynamic: summary
